hos_secsuite/__init__.py
hos_secsuite/console/ascii_logo.py
hos_secsuite/console/command_parser.py
hos_secsuite/console/console_app.py
hos_secsuite/core/base_module.py
hos_secsuite/core/registry.py
hos_secsuite/core/runner.py
hos_secsuite/mcp/__init__.py
hos_secsuite/mcp/schemas.py
hos_secsuite/mcp/server.py
hos_secsuite/mcp/tools/__init__.py
hos_secsuite/mcp/tools/nmap_tool.py
hos_secsuite/mcp/tools/pcap_tool.py
hos_secsuite/mcp/tools/vuln_tool.py
hos_secsuite/modules/web/proxy/mitmproxy_integration.py
hos_secsuite/modules/web/proxy/proxy_py_integration.py
hos_secsuite/modules/web/request/httpx_client.py
hos_secsuite/modules/web/request/requests_client.py
hos_secsuite/modules/web/request/scrapy_integration.py
hos_secsuite/modules/web/vuln/dirsearch_integration.py
hos_secsuite/modules/web/vuln/sqlmap_integration.py
hos_secsuite/modules/web/vuln/xsstrike_integration.py
hos_secsuite/utils/__init__.py
hos_secsuite/utils/cmd_exec.py
hos_secsuite/utils/logger.py
hos_secsuite/utils/os_check.py
hos_secsuite/utils/sanitizer.py
hos_secsuite-0.1.4.dist-info/METADATA
hos_secsuite-0.1.4.dist-info/WHEEL
hos_secsuite-0.1.4.dist-info/entry_points.txt
hos_secsuite-0.1.4.dist-info/top_level.txt
hos_secsuite-0.1.4.dist-info/RECORD
