Metadata-Version: 2.4
Name: HOS_SECSUITE
Version: 0.1.4
Summary: HOS SecSuite: 模块化网络安全工具包（防御优先）
Author-email: HOS <security@example.com>
License: Apache-2.0
Project-URL: Homepage, https://example.com/hos-secsuite
Project-URL: Repository, https://example.com/hos-secsuite
Project-URL: Documentation, https://example.com/hos-secsuite/docs
Project-URL: Issues, https://example.com/hos-secsuite/issues
Keywords: security,network,defense,mcp,cli,penetration-testing,vulnerability-scanning,proxy,web-security
Classifier: Development Status :: 3 - Alpha
Classifier: Intended Audience :: Developers
Classifier: Intended Audience :: Information Technology
Classifier: Intended Audience :: System Administrators
Classifier: License :: OSI Approved :: Apache Software License
Classifier: Operating System :: OS Independent
Classifier: Programming Language :: Python :: 3
Classifier: Programming Language :: Python :: 3.8
Classifier: Programming Language :: Python :: 3.9
Classifier: Programming Language :: Python :: 3.10
Classifier: Programming Language :: Python :: 3.11
Classifier: Programming Language :: Python :: 3.12
Classifier: Topic :: Security
Classifier: Topic :: System :: Networking :: Monitoring
Classifier: Topic :: Utilities
Requires-Python: >=3.8
Requires-Dist: mitmproxy>=10.0.0
Requires-Dist: proxy.py>=2.4.0
Requires-Dist: requests>=2.31.0
Requires-Dist: httpx>=0.25.0
Requires-Dist: scrapy>=2.11.0
Requires-Dist: beautifulsoup4>=4.12.0
Requires-Dist: fastapi>=0.104.0
Requires-Dist: uvicorn>=0.24.0
Requires-Dist: websockets>=11.0.0
Requires-Dist: scapy>=2.5.0
Requires-Dist: python-dotenv>=1.0.0
Provides-Extra: dev
Requires-Dist: pytest>=7.4.0; extra == "dev"
Requires-Dist: pytest-asyncio>=0.21.0; extra == "dev"
Requires-Dist: pytest-cov>=4.0.0; extra == "dev"
Requires-Dist: black>=23.0.0; extra == "dev"
Requires-Dist: isort>=5.12.0; extra == "dev"
Requires-Dist: flake8>=6.0.0; extra == "dev"
